epublib/__init__.py
epublib/create.py
epublib/css.py
epublib/exceptions.py
epublib/identifier.py
epublib/media_type.py
epublib/parse.py
epublib/py.typed
epublib/soup.py
epublib/source.py
epublib/types.py
epublib/util.py
epublib/xml_element.py
epublib/nav/__init__.py
epublib/nav/reset.py
epublib/nav/resource.py
epublib/nav/util.py
epublib/ncx/__init__.py
epublib/ncx/reset.py
epublib/ncx/resource.py
epublib/package/__init__.py
epublib/package/guide.py
epublib/package/manifest.py
epublib/package/metadata.py
epublib/package/properties.py
epublib/package/resource.py
epublib/package/spine.py
epublib/resources/__init__.py
epublib/resources/create.py
epublib/resources/manager.py
epublib/resources/rename.py
epublib/resources/window.py
epublib-0.1.6.dist-info/METADATA
epublib-0.1.6.dist-info/WHEEL
epublib-0.1.6.dist-info/licenses/LICENSE
epublib-0.1.6.dist-info/RECORD
