Metadata-Version: 2.4
Name: epublib
Version: 0.1.6
Summary: An EPUB3 python library
Project-URL: Homepage, https://gitlab.com/joaoseckler/epublib
Project-URL: Documentation, https://epub-lib.readthedocs.org
Project-URL: Repository, https://gitlab.com/joaoseckler/epublib
Project-URL: Issues, https://gitlab.com/joaoseckler/epublib/issues
Author-email: João Seckler <jseckler@riseup.net>
License-Expression: MIT
License-File: LICENSE
Keywords: ebook,epub,epub3
Classifier: Development Status :: 3 - Alpha
Classifier: Framework :: Pytest
Classifier: Intended Audience :: Developers
Classifier: License :: OSI Approved :: MIT License
Classifier: Natural Language :: English
Requires-Python: >=3.13
Requires-Dist: beautifulsoup4>=4.14.2
Requires-Dist: lxml>=6.0.2
